semilimes/__init__.py
semilimes/semilimes.py
semilimes-0.1.0.dist-info/LICENSE.txt
semilimes-0.1.0.dist-info/METADATA
semilimes-0.1.0.dist-info/WHEEL
semilimes-0.1.0.dist-info/top_level.txt
semilimes-0.1.0.dist-info/RECORD
